modulo_pablo/__init__.py
modulo_pablo/modulo.py
modulo_pablo/modulo2.py
modulo_pablo-0.1.4.dist-info/LICENSE
modulo_pablo-0.1.4.dist-info/METADATA
modulo_pablo-0.1.4.dist-info/WHEEL
modulo_pablo-0.1.4.dist-info/top_level.txt
modulo_pablo-0.1.4.dist-info/RECORD
