Metadata-Version: 2.1
Name: modulo_pablo
Version: 0.1.4
Summary: Paquete creado con fines educativos. Mas informacion: github.com/Duz-Dev
Author-email: Ruben Chavez <pablo.dev.academy@gmail.com>
License: MIT License
Project-URL: Homepage, https://github.com/Duz-Dev/modulo-pablo
Project-URL: Download, https://github.com/Duz-Dev/modulo-pablo/tarball/0.1.3
Keywords: testing,logging,example
Classifier: Programming Language :: Python :: 3
Classifier: License :: OSI Approved :: MIT License
Classifier: Operating System :: OS Independent
License-File: LICENSE
Requires-Dist: pillow
Requires-Dist: requests
